colorbykawa/__init__.py
colorbykawa-4.0.5.dist-info/LICENSE
colorbykawa-4.0.5.dist-info/METADATA
colorbykawa-4.0.5.dist-info/WHEEL
colorbykawa-4.0.5.dist-info/top_level.txt
colorbykawa-4.0.5.dist-info/RECORD
